linked_properties.py
linked_properties-1.0.0b1.dist-info/.DS_Store
linked_properties-1.0.0b1.dist-info/DESCRIPTION.rst
linked_properties-1.0.0b1.dist-info/METADATA
linked_properties-1.0.0b1.dist-info/RECORD
linked_properties-1.0.0b1.dist-info/WHEEL
linked_properties-1.0.0b1.dist-info/metadata.json
linked_properties-1.0.0b1.dist-info/top_level.txt
