Metadata-Version: 2.0
Name: linked-properties
Version: 1.0.0b1
Summary: This library allows you to link properties, so if one is changed the others change accordingly.
Home-page: https://github.com/CNLambda/linked_properties/
Author: CNLambda
Author-email: dodo2998@gmail.com
License: UNLICENSE
Keywords: linking properties
Platform: UNKNOWN
Classifier: Development Status :: 4 - Beta
Classifier: Intended Audience :: Developers
Classifier: License :: Freely Distributable
Classifier: Programming Language :: Python :: 3
Classifier: Programming Language :: Python :: 3.5
